metapg/cli/__init__.py
metapg/cli/app.py
metapg/cli/utils.py
metapg/cli/commands/__init__.py
metapg/cli/commands/migration.py
metapg/cli/commands/pool.py
metapg/cli/py.typed
metapg_cli-0.0.2.dist-info/METADATA
metapg_cli-0.0.2.dist-info/WHEEL
metapg_cli-0.0.2.dist-info/entry_points.txt
metapg_cli-0.0.2.dist-info/RECORD
